pkgdependencymanager/__init__.py
pkgdependencymanager/__main__.py
pkgdependencymanager/config.py
pkgdependencymanager/util.py
pkg_dependency_manager-1.0.3.dist-info/LICENSE
pkg_dependency_manager-1.0.3.dist-info/METADATA
pkg_dependency_manager-1.0.3.dist-info/WHEEL
pkg_dependency_manager-1.0.3.dist-info/top_level.txt
pkg_dependency_manager-1.0.3.dist-info/RECORD
