Metadata-Version: 2.1
Name: pkg-dependency-manager
Version: 1.0.3
Summary: A system package dependency manager, written in Python 3.9.
Home-page: https://github.com/yodasoda1219/pkg-dependency-manager
Author: ys1219
Author-email: ys1219@cosmodash.com
License: UNKNOWN
Platform: UNKNOWN
Classifier: Programming Language :: Python :: 3
Classifier: Operating System :: OS Independent
Requires-Python: >=3.9.6
License-File: LICENSE
